{
	"name": "ds_lookupCustomer",
	"properties": {
		"linkedServiceName": {
			"referenceName": "ls_adls",
			"type": "LinkedServiceReference"
		},
		"annotations": [],
		"type": "DelimitedText",
		"typeProperties": {
			"location": {
				"type": "AzureBlobFSLocation",
				"fileName": "Customers.csv",
				"folderPath": "Lookup",
				"fileSystem": "mycontainer"
			},
			"columnDelimiter": ",",
			"escapeChar": "\\",
			"firstRowAsHeader": true,
			"quoteChar": "\""
		},
		"schema": [
			{
				"name": "CustomerKey",
				"type": "String"
			},
			{
				"name": "FullName",
				"type": "String"
			}
		]
	}
}